ckan_editor_utils/__init__.py
ckan_editor_utils/ckan_editor_utils.py
ckan_editor_utils-0.1.9.dist-info/LICENSE.txt
ckan_editor_utils-0.1.9.dist-info/WHEEL
ckan_editor_utils-0.1.9.dist-info/METADATA
ckan_editor_utils-0.1.9.dist-info/RECORD
