Metadata-Version: 2.1
Name: ckan-editor-utils
Version: 0.1.9
Summary: Utilities for editing CKAN using its API.
Home-page: https://github.com/ericmccowan/ckan-editor-utils
License: MIT
Author: Eric McCowan
Author-email: eric.mccowan@servian.com
Requires-Python: >=3.6,<4.0
Classifier: License :: OSI Approved :: MIT License
Classifier: Programming Language :: Python :: 3
Classifier: Programming Language :: Python :: 3.6
Classifier: Programming Language :: Python :: 3.7
Classifier: Programming Language :: Python :: 3.8
Classifier: Programming Language :: Python :: 3.9
Requires-Dist: boto3 (>=1.15.16,<2.0.0)
Requires-Dist: requests (>=2.24.0,<3.0.0)
Project-URL: Repository, https://github.com/ericmccowan/ckan-editor-utils
